manish/__init__.py
manish/intro.py
manishIntro-0.0.1.dist-info/METADATA
manishIntro-0.0.1.dist-info/WHEEL
manishIntro-0.0.1.dist-info/top_level.txt
manishIntro-0.0.1.dist-info/RECORD
