Metadata-Version: 2.1
Name: manishIntro
Version: 0.0.1
Summary: A python module for Intorducing Manish
Author: Manish Kumar
Author-email: officialmanishkr98@gmail.com
License: GNU
Keywords: manish,sayHi
Classifier: Development Status :: 5 - Production/Stable
Classifier: Intended Audience :: Education
Classifier: Operating System :: Microsoft :: Windows
Classifier: Operating System :: POSIX :: Linux
Classifier: Operating System :: MacOS :: MacOS X
Classifier: License :: OSI Approved :: GNU General Public License (GPL)
Classifier: Programming Language :: Python :: 3
